[
  {
    "elo__prob": 0.495,
    "elo__r1": 1500.0,
    "elo__r2": 1503.488,
    "matchup__character_o": "argagarg",
    "matchup__character_p": "degrey",
    "matchup__mup": null,
    "matchup__non_mirror": 1,
    "min_games__min_games_player_o": false,
    "min_games__min_games_player_p": false,
    "min_games__player_o": "Reaverb Tau",
    "min_games__player_p": "Graskell",
    "opponent": "Reaverb Tau",
    "pc_elo__prob": 0.5,
    "pc_elo__r1": 1500.0,
    "pc_elo__r2": 1500.0,
    "player": "Graskell",
    "render__match_date": 1429833600000,
    "render__public": true,
    "render__win": 1
  },
  {
    "elo__prob": 0.495,
    "elo__r1": 1500.0,
    "elo__r2": 1503.488,
    "matchup__character_o": "argagarg",
    "matchup__character_p": "setsuki",
    "matchup__mup": null,
    "matchup__non_mirror": 1,
    "min_games__min_games_player_o": false,
    "min_games__min_games_player_p": false,
    "min_games__player_o": "Reaverb Tau",
    "min_games__player_p": "Graskell",
    "opponent": "Reaverb Tau",
    "pc_elo__prob": 0.5,
    "pc_elo__r1": 1500.0,
    "pc_elo__r2": 1500.0,
    "player": "Graskell",
    "render__match_date": 1429833600000,
    "render__public": true,
    "render__win": 0
  },
  {
    "elo__prob": 0.473,
    "elo__r1": 1481.013,
    "elo__r2": 1500.0,
    "matchup__character_o": "midori",
    "matchup__character_p": "degrey",
    "matchup__mup": null,
    "matchup__non_mirror": 1,
    "min_games__min_games_player_o": false,
    "min_games__min_games_player_p": false,
    "min_games__player_o": "Paulie",
    "min_games__player_p": "Graskell",
    "opponent": "Paulie",
    "pc_elo__prob": 0.497,
    "pc_elo__r1": 1498.022,
    "pc_elo__r2": 1500.0,
    "player": "Graskell",
    "render__match_date": 1429833600000,
    "render__public": true,
    "render__win": -1
  },
  {
    "elo__prob": 0.505,
    "elo__r1": 1503.488,
    "elo__r2": 1500.0,
    "matchup__character_o": "setsuki",
    "matchup__character_p": "degrey",
    "matchup__mup": null,
    "matchup__non_mirror": 1,
    "min_games__min_games_player_o": false,
    "min_games__min_games_player_p": false,
    "min_games__player_o": "Reaverb Tau",
    "min_games__player_p": "Graskell",
    "opponent": "Reaverb Tau",
    "pc_elo__prob": 0.5,
    "pc_elo__r1": 1500.0,
    "pc_elo__r2": 1500.0,
    "player": "Graskell",
    "render__match_date": 1429833600000,
    "render__public": true,
    "render__win": -2
  },
  {
    "elo__prob": 0.473,
    "elo__r1": 1481.013,
    "elo__r2": 1500.0,
    "matchup__character_o": "grave",
    "matchup__character_p": "degrey",
    "matchup__mup": null,
    "matchup__non_mirror": 1,
    "min_games__min_games_player_o": false,
    "min_games__min_games_player_p": false,
    "min_games__player_o": "Paulie",
    "min_games__player_p": "Graskell",
    "opponent": "Paulie",
    "pc_elo__prob": 0.5,
    "pc_elo__r1": 1499.996,
    "pc_elo__r2": 1500.0,
    "player": "Graskell",
    "render__match_date": 1429833600000,
    "render__public": true,
    "render__win": -1
  },
  {
    "elo__prob": 0.544,
    "elo__r1": 1506.021,
    "elo__r2": 1475.024,
    "matchup__character_o": "zane",
    "matchup__character_p": "degrey",
    "matchup__mup": "degrey-zane",
    "matchup__non_mirror": 1,
    "min_games__min_games_player_o": false,
    "min_games__min_games_player_p": false,
    "min_games__player_o": "noshots00",
    "min_games__player_p": "Graskell",
    "opponent": "noshots00",
    "pc_elo__prob": 0.502,
    "pc_elo__r1": 1500.992,
    "pc_elo__r2": 1499.535,
    "player": "Graskell",
    "render__match_date": 1430438400000,
    "render__public": true,
    "render__win": 0
  },
  {
    "elo__prob": 0.544,
    "elo__r1": 1506.021,
    "elo__r2": 1475.024,
    "matchup__character_o": "zane",
    "matchup__character_p": "degrey",
    "matchup__mup": "degrey-zane",
    "matchup__non_mirror": 1,
    "min_games__min_games_player_o": false,
    "min_games__min_games_player_p": false,
    "min_games__player_o": "noshots00",
    "min_games__player_p": "Graskell",
    "opponent": "noshots00",
    "pc_elo__prob": 0.502,
    "pc_elo__r1": 1500.992,
    "pc_elo__r2": 1499.535,
    "player": "Graskell",
    "render__match_date": 1430438400000,
    "render__public": true,
    "render__win": 0
  },
  {
    "elo__prob": 0.456,
    "elo__r1": 1475.024,
    "elo__r2": 1506.021,
    "matchup__character_o": "lum",
    "matchup__character_p": "degrey",
    "matchup__mup": null,
    "matchup__non_mirror": 1,
    "min_games__min_games_player_o": false,
    "min_games__min_games_player_p": false,
    "min_games__player_o": "noshots00",
    "min_games__player_p": "Graskell",
    "opponent": "noshots00",
    "pc_elo__prob": 0.499,
    "pc_elo__r1": 1500.0,
    "pc_elo__r2": 1500.992,
    "player": "Graskell",
    "render__match_date": 1430438400000,
    "render__public": true,
    "render__win": -1
  },
  {
    "elo__prob": 0.456,
    "elo__r1": 1475.024,
    "elo__r2": 1506.021,
    "matchup__character_o": "lum",
    "matchup__character_p": "degrey",
    "matchup__mup": null,
    "matchup__non_mirror": 1,
    "min_games__min_games_player_o": false,
    "min_games__min_games_player_p": false,
    "min_games__player_o": "noshots00",
    "min_games__player_p": "Graskell",
    "opponent": "noshots00",
    "pc_elo__prob": 0.499,
    "pc_elo__r1": 1500.0,
    "pc_elo__r2": 1500.992,
    "player": "Graskell",
    "render__match_date": 1430438400000,
    "render__public": true,
    "render__win": -2
  }
]