[
  {
    "glicko__prob": 0.408,
    "glicko__rdo": 34.971,
    "glicko__rdp": 43.158,
    "glicko__ro": 1622.605,
    "glicko__rp": 1556.81,
    "glicko__vo": 0.059,
    "glicko__vp": 0.059,
    "matchup__character_o": "setsuki",
    "matchup__character_p": "grave",
    "matchup__mup": "grave-setsuki",
    "matchup__non_mirror": 1,
    "min_games__min_games_player_o": false,
    "min_games__min_games_player_p": false,
    "min_games__player_o": "Fivec",
    "min_games__player_p": "bontakun",
    "opponent": "Fivec",
    "pc_glicko__prob": 0.423,
    "pc_glicko__rdo": 25.584,
    "pc_glicko__rdp": 29.975,
    "pc_glicko__ro": 1567.434,
    "pc_glicko__rp": 1513.247,
    "pc_glicko__vo": 0.027,
    "pc_glicko__vp": 0.027,
    "player": "bontakun",
    "render__match_date": 1428710400000,
    "render__public": true,
    "render__win": false
  },
  {
    "glicko__prob": 0.408,
    "glicko__rdo": 34.971,
    "glicko__rdp": 43.158,
    "glicko__ro": 1622.605,
    "glicko__rp": 1556.81,
    "glicko__vo": 0.059,
    "glicko__vp": 0.059,
    "matchup__character_o": "setsuki",
    "matchup__character_p": "grave",
    "matchup__mup": "grave-setsuki",
    "matchup__non_mirror": 1,
    "min_games__min_games_player_o": false,
    "min_games__min_games_player_p": false,
    "min_games__player_o": "Fivec",
    "min_games__player_p": "bontakun",
    "opponent": "Fivec",
    "pc_glicko__prob": 0.423,
    "pc_glicko__rdo": 25.584,
    "pc_glicko__rdp": 29.975,
    "pc_glicko__ro": 1567.434,
    "pc_glicko__rp": 1513.247,
    "pc_glicko__vo": 0.027,
    "pc_glicko__vp": 0.027,
    "player": "bontakun",
    "render__match_date": 1428710400000,
    "render__public": true,
    "render__win": false
  },
  {
    "glicko__prob": 0.368,
    "glicko__rdo": 39.498,
    "glicko__rdp": 43.158,
    "glicko__ro": 1652.591,
    "glicko__rp": 1556.81,
    "glicko__vo": 0.058,
    "glicko__vp": 0.059,
    "matchup__character_o": "argagarg",
    "matchup__character_p": "grave",
    "matchup__mup": "grave-argagarg",
    "matchup__non_mirror": 1,
    "min_games__min_games_player_o": false,
    "min_games__min_games_player_p": false,
    "min_games__player_o": "deluks917",
    "min_games__player_p": "bontakun",
    "opponent": "deluks917",
    "pc_glicko__prob": 0.477,
    "pc_glicko__rdo": 38.757,
    "pc_glicko__rdp": 29.975,
    "pc_glicko__ro": 1529.546,
    "pc_glicko__rp": 1513.247,
    "pc_glicko__vo": 0.027,
    "pc_glicko__vp": 0.027,
    "player": "bontakun",
    "render__match_date": 1428710400000,
    "render__public": true,
    "render__win": false
  },
  {
    "glicko__prob": 0.368,
    "glicko__rdo": 39.498,
    "glicko__rdp": 43.158,
    "glicko__ro": 1652.591,
    "glicko__rp": 1556.81,
    "glicko__vo": 0.058,
    "glicko__vp": 0.059,
    "matchup__character_o": "argagarg",
    "matchup__character_p": "grave",
    "matchup__mup": "grave-argagarg",
    "matchup__non_mirror": 1,
    "min_games__min_games_player_o": false,
    "min_games__min_games_player_p": false,
    "min_games__player_o": "deluks917",
    "min_games__player_p": "bontakun",
    "opponent": "deluks917",
    "pc_glicko__prob": 0.477,
    "pc_glicko__rdo": 38.757,
    "pc_glicko__rdp": 29.975,
    "pc_glicko__ro": 1529.546,
    "pc_glicko__rp": 1513.247,
    "pc_glicko__vo": 0.027,
    "pc_glicko__vp": 0.027,
    "player": "bontakun",
    "render__match_date": 1428710400000,
    "render__public": true,
    "render__win": false
  },
  {
    "glicko__prob": 0.497,
    "glicko__rdo": 34.579,
    "glicko__rdp": 43.158,
    "glicko__ro": 1558.874,
    "glicko__rp": 1556.81,
    "glicko__vo": 0.059,
    "glicko__vp": 0.059,
    "matchup__character_o": "gloria",
    "matchup__character_p": "grave",
    "matchup__mup": "grave-gloria",
    "matchup__non_mirror": 1,
    "min_games__min_games_player_o": false,
    "min_games__min_games_player_p": false,
    "min_games__player_o": "enomus",
    "min_games__player_p": "bontakun",
    "opponent": "enomus",
    "pc_glicko__prob": 0.481,
    "pc_glicko__rdo": 29.012,
    "pc_glicko__rdp": 29.975,
    "pc_glicko__ro": 1526.689,
    "pc_glicko__rp": 1513.247,
    "pc_glicko__vo": 0.027,
    "pc_glicko__vp": 0.027,
    "player": "bontakun",
    "render__match_date": 1428710400000,
    "render__public": true,
    "render__win": true
  },
  {
    "glicko__prob": 0.497,
    "glicko__rdo": 34.579,
    "glicko__rdp": 43.158,
    "glicko__ro": 1558.874,
    "glicko__rp": 1556.81,
    "glicko__vo": 0.059,
    "glicko__vp": 0.059,
    "matchup__character_o": "argagarg",
    "matchup__character_p": "grave",
    "matchup__mup": "grave-argagarg",
    "matchup__non_mirror": 1,
    "min_games__min_games_player_o": false,
    "min_games__min_games_player_p": false,
    "min_games__player_o": "enomus",
    "min_games__player_p": "bontakun",
    "opponent": "enomus",
    "pc_glicko__prob": 0.501,
    "pc_glicko__rdo": 35.834,
    "pc_glicko__rdp": 29.975,
    "pc_glicko__ro": 1512.325,
    "pc_glicko__rp": 1513.247,
    "pc_glicko__vo": 0.027,
    "pc_glicko__vp": 0.027,
    "player": "bontakun",
    "render__match_date": 1428710400000,
    "render__public": true,
    "render__win": true
  },
  {
    "glicko__prob": 0.412,
    "glicko__rdo": 36.07,
    "glicko__rdp": 43.158,
    "glicko__ro": 1619.753,
    "glicko__rp": 1556.81,
    "glicko__vo": 0.059,
    "glicko__vp": 0.059,
    "matchup__character_o": "zane",
    "matchup__character_p": "grave",
    "matchup__mup": "grave-zane",
    "matchup__non_mirror": 1,
    "min_games__min_games_player_o": false,
    "min_games__min_games_player_p": false,
    "min_games__player_o": "Southpaw Hare",
    "min_games__player_p": "bontakun",
    "opponent": "Southpaw Hare",
    "pc_glicko__prob": 0.396,
    "pc_glicko__rdo": 29.617,
    "pc_glicko__rdp": 29.975,
    "pc_glicko__ro": 1587.306,
    "pc_glicko__rp": 1513.247,
    "pc_glicko__vo": 0.027,
    "pc_glicko__vp": 0.027,
    "player": "bontakun",
    "render__match_date": 1428710400000,
    "render__public": true,
    "render__win": false
  },
  {
    "glicko__prob": 0.412,
    "glicko__rdo": 36.07,
    "glicko__rdp": 43.158,
    "glicko__ro": 1619.753,
    "glicko__rp": 1556.81,
    "glicko__vo": 0.059,
    "glicko__vp": 0.059,
    "matchup__character_o": "zane",
    "matchup__character_p": "grave",
    "matchup__mup": "grave-zane",
    "matchup__non_mirror": 1,
    "min_games__min_games_player_o": false,
    "min_games__min_games_player_p": false,
    "min_games__player_o": "Southpaw Hare",
    "min_games__player_p": "bontakun",
    "opponent": "Southpaw Hare",
    "pc_glicko__prob": 0.396,
    "pc_glicko__rdo": 29.617,
    "pc_glicko__rdp": 29.975,
    "pc_glicko__ro": 1587.306,
    "pc_glicko__rp": 1513.247,
    "pc_glicko__vo": 0.027,
    "pc_glicko__vp": 0.027,
    "player": "bontakun",
    "render__match_date": 1428710400000,
    "render__public": true,
    "render__win": false
  },
  {
    "glicko__prob": 0.372,
    "glicko__rdo": 38.937,
    "glicko__rdp": 43.158,
    "glicko__ro": 1649.064,
    "glicko__rp": 1556.81,
    "glicko__vo": 0.058,
    "glicko__vp": 0.059,
    "matchup__character_o": "argagarg",
    "matchup__character_p": "grave",
    "matchup__mup": "grave-argagarg",
    "matchup__non_mirror": 1,
    "min_games__min_games_player_o": false,
    "min_games__min_games_player_p": false,
    "min_games__player_o": "Jengajam",
    "min_games__player_p": "bontakun",
    "opponent": "Jengajam",
    "pc_glicko__prob": 0.404,
    "pc_glicko__rdo": 33.376,
    "pc_glicko__rdp": 29.975,
    "pc_glicko__ro": 1581.318,
    "pc_glicko__rp": 1513.247,
    "pc_glicko__vo": 0.027,
    "pc_glicko__vp": 0.027,
    "player": "bontakun",
    "render__match_date": 1428710400000,
    "render__public": true,
    "render__win": true
  },
  {
    "glicko__prob": 0.372,
    "glicko__rdo": 38.937,
    "glicko__rdp": 43.158,
    "glicko__ro": 1649.064,
    "glicko__rp": 1556.81,
    "glicko__vo": 0.058,
    "glicko__vp": 0.059,
    "matchup__character_o": "menelker",
    "matchup__character_p": "grave",
    "matchup__mup": "grave-menelker",
    "matchup__non_mirror": 1,
    "min_games__min_games_player_o": false,
    "min_games__min_games_player_p": false,
    "min_games__player_o": "Jengajam",
    "min_games__player_p": "bontakun",
    "opponent": "Jengajam",
    "pc_glicko__prob": 0.501,
    "pc_glicko__rdo": 32.158,
    "pc_glicko__rdp": 29.975,
    "pc_glicko__ro": 1512.452,
    "pc_glicko__rp": 1513.247,
    "pc_glicko__vo": 0.027,
    "pc_glicko__vp": 0.027,
    "player": "bontakun",
    "render__match_date": 1428710400000,
    "render__public": true,
    "render__win": true
  },
  {
    "glicko__prob": 0.368,
    "glicko__rdo": 39.498,
    "glicko__rdp": 43.158,
    "glicko__ro": 1652.591,
    "glicko__rp": 1556.81,
    "glicko__vo": 0.058,
    "glicko__vp": 0.059,
    "matchup__character_o": "argagarg",
    "matchup__character_p": "grave",
    "matchup__mup": "grave-argagarg",
    "matchup__non_mirror": 1,
    "min_games__min_games_player_o": false,
    "min_games__min_games_player_p": false,
    "min_games__player_o": "deluks917",
    "min_games__player_p": "bontakun",
    "opponent": "deluks917",
    "pc_glicko__prob": 0.477,
    "pc_glicko__rdo": 38.757,
    "pc_glicko__rdp": 29.975,
    "pc_glicko__ro": 1529.546,
    "pc_glicko__rp": 1513.247,
    "pc_glicko__vo": 0.027,
    "pc_glicko__vp": 0.027,
    "player": "bontakun",
    "render__match_date": 1428710400000,
    "render__public": true,
    "render__win": true
  },
  {
    "glicko__prob": 0.497,
    "glicko__rdo": 34.579,
    "glicko__rdp": 43.158,
    "glicko__ro": 1558.874,
    "glicko__rp": 1556.81,
    "glicko__vo": 0.059,
    "glicko__vp": 0.059,
    "matchup__character_o": "gloria",
    "matchup__character_p": "grave",
    "matchup__mup": "grave-gloria",
    "matchup__non_mirror": 1,
    "min_games__min_games_player_o": false,
    "min_games__min_games_player_p": false,
    "min_games__player_o": "enomus",
    "min_games__player_p": "bontakun",
    "opponent": "enomus",
    "pc_glicko__prob": 0.481,
    "pc_glicko__rdo": 29.012,
    "pc_glicko__rdp": 29.975,
    "pc_glicko__ro": 1526.689,
    "pc_glicko__rp": 1513.247,
    "pc_glicko__vo": 0.027,
    "pc_glicko__vp": 0.027,
    "player": "bontakun",
    "render__match_date": 1428710400000,
    "render__public": true,
    "render__win": false
  },
  {
    "glicko__prob": 0.412,
    "glicko__rdo": 36.07,
    "glicko__rdp": 43.158,
    "glicko__ro": 1619.753,
    "glicko__rp": 1556.81,
    "glicko__vo": 0.059,
    "glicko__vp": 0.059,
    "matchup__character_o": "zane",
    "matchup__character_p": "grave",
    "matchup__mup": "grave-zane",
    "matchup__non_mirror": 1,
    "min_games__min_games_player_o": false,
    "min_games__min_games_player_p": false,
    "min_games__player_o": "Southpaw Hare",
    "min_games__player_p": "bontakun",
    "opponent": "Southpaw Hare",
    "pc_glicko__prob": 0.396,
    "pc_glicko__rdo": 29.617,
    "pc_glicko__rdp": 29.975,
    "pc_glicko__ro": 1587.306,
    "pc_glicko__rp": 1513.247,
    "pc_glicko__vo": 0.027,
    "pc_glicko__vp": 0.027,
    "player": "bontakun",
    "render__match_date": 1428710400000,
    "render__public": true,
    "render__win": true
  }
]