[{"tournament_name":"Los Angeles Meetup 2","match_date":1438992000000,"player_1":"GiesyDragon","character_1":"Jaina","win":0,"character_2":"Setsuki","player_2":"Fivec","elo_before_1":1480.5,"elo_before_2":1748.53753},{"tournament_name":"Los Angeles Meetup 2","match_date":1438992000000,"player_1":"GiesyDragon","character_1":"Jaina","win":0,"character_2":"Setsuki","player_2":"Fivec","elo_before_1":1480.5,"elo_before_2":1748.53753},{"tournament_name":"Los Angeles Meetup 2","match_date":1438992000000,"player_1":"GiesyDragon","character_1":"Jaina","win":0,"character_2":"Setsuki","player_2":"Fivec","elo_before_1":1480.5,"elo_before_2":1748.53753},{"tournament_name":"Los Angeles Meetup 2","match_date":1438992000000,"player_1":"GiesyDragon","character_1":"Jaina","win":0,"character_2":"Midori","player_2":"Leontes","elo_before_1":1480.5,"elo_before_2":1938.0360865},{"tournament_name":"Los Angeles Meetup 2","match_date":1438992000000,"player_1":"GiesyDragon","character_1":"Jaina","win":0,"character_2":"Midori","player_2":"Leontes","elo_before_1":1480.5,"elo_before_2":1938.0360865},{"tournament_name":"Los Angeles Meetup 2","match_date":1438992000000,"player_1":"GiesyDragon","character_1":"Jaina","win":0,"character_2":"Midori","player_2":"Leontes","elo_before_1":1480.5,"elo_before_2":1938.0360865},{"tournament_name":"Los Angeles Meetup 2","match_date":1438992000000,"player_1":"GiesyDragon","character_1":"Jaina","win":1,"character_2":"Setsuki","player_2":"Fivec","elo_before_1":1480.5,"elo_before_2":1748.53753}]